setup.py
militia/__init__.py
militia.egg-info/PKG-INFO
militia.egg-info/SOURCES.txt
militia.egg-info/dependency_links.txt
militia.egg-info/not-zip-safe
militia.egg-info/top_level.txt
militia/tools/__init__.py
militia/tools/facebook/__init__.py
militia/tools/facebook/fb_utils.py
militia/tools/google/__init__.py
militia/tools/google/gmap_utils.py
militia/tools/instagram/__init__.py
militia/tools/instagram/instagram_utils.py
militia/tools/twitter/__init__.py
militia/tools/twitter/svm-tweets.py
militia/tools/twitter/twitter_utils.py
militia/tools/wikipedia/__init__.py
militia/tools/wikipedia/wiki_utils.py