Metadata-Version: 1.0
Name: militia
Version: 0.2
Summary: Intelligent and intuitive applications for analysts
Home-page: http://github.com/vlall/militia
Author: V Lall, M Bartoli
Author-email: vishal.h.lall@gmail.com
License: BSD
Platform: UNKNOWN
